lnas/__init__.py
lnas/exceptions.py
lnas/fmt.py
lnas/geometry.py
lnas/stl.py
lnas/transformations.py
lnas/utils.py
aerosim_lnas-0.6.4.dist-info/METADATA
aerosim_lnas-0.6.4.dist-info/WHEEL
aerosim_lnas-0.6.4.dist-info/licenses/LICENSE
aerosim_lnas-0.6.4.dist-info/RECORD
